README.md
setup.cfg
setup.py
homekit/__init__.py
homekit/accessoryserver.py
homekit/add_additional_pairing.py
homekit/discover.py
homekit/discover_ble.py
homekit/exceptions.py
homekit/finish_add_remote_pairing.py
homekit/get_accessories.py
homekit/get_camera_information.py
homekit/get_characteristic.py
homekit/get_events.py
homekit/get_image_snapshot.py
homekit/identify.py
homekit/init_controller_storage.py
homekit/list_pairings.py
homekit/log_support.py
homekit/pair.py
homekit/pair_ble.py
homekit/prepare_add_remote_pairing.py
homekit/put_characteristic.py
homekit/remove_pairing.py
homekit/tools.py
homekit/controller/__init__.py
homekit/controller/additional_pairing.py
homekit/controller/controller.py
homekit/controller/ip_implementation.py
homekit/controller/tools.py
homekit/controller/ble_impl/__init__.py
homekit/controller/ble_impl/device.py
homekit/controller/ble_impl/discovery.py
homekit/controller/ble_impl/gatt.py
homekit/controller/ble_impl/manufacturer_data.py
homekit/controller/ble_impl/tools.py
homekit/crypto/__init__.py
homekit/crypto/chacha20poly1305.py
homekit/crypto/srp.py
homekit/http_impl/__init__.py
homekit/http_impl/contentTypes.py
homekit/http_impl/http_client.py
homekit/http_impl/response.py
homekit/http_impl/secure_http.py
homekit/model/__init__.py
homekit/model/categories.py
homekit/model/feature_flags.py
homekit/model/mixin.py
homekit/model/status_flags.py
homekit/model/characteristics/__init__.py
homekit/model/characteristics/abstract_characteristic.py
homekit/model/characteristics/administrator_only_access.py
homekit/model/characteristics/audio_feedback.py
homekit/model/characteristics/battery_level.py
homekit/model/characteristics/brightness.py
homekit/model/characteristics/characteristic_formats.py
homekit/model/characteristics/characteristic_permissions.py
homekit/model/characteristics/characteristic_types.py
homekit/model/characteristics/characteristic_units.py
homekit/model/characteristics/current_heating_cooling_state.py
tlv8.egg-info/PKG-INFO
tlv8.egg-info/SOURCES.txt
tlv8.egg-info/dependency_links.txt
tlv8.egg-info/top_level.txt