Metadata-Version: 2.1
Name: tlv8
Version: 0.0.1
Summary: DESCRIPTION
Home-page: https://github.com/jlusiardi/tlv8_python
Author: Joachim Lusiardi
Author-email: pypi@lusiardi.de
License: Apache License 2.0
Download-URL: https://github.com/jlusiardi/tlv8_python/archive/0.0.1.tar.gz
Keywords: TLV,Type-Length-Value,tlv8
Platform: UNKNOWN
Classifier: License :: OSI Approved :: Apache Software License
Classifier: Topic :: Home Automation
Classifier: Intended Audience :: Developers
Classifier: Intended Audience :: End Users/Desktop
